{
  "fetchedAt": "2026-02-18T19:44:00.733Z",
  "companies": {
    "salesforce": {
      "name": "Salesforce",
      "targetRole": "Senior Member of Technical Staff (SMTS)",
      "careersUrl": "https://careers.salesforce.com/en/jobs/?country=India",
      "jobs": [
        {
          "id": "JR321153",
          "title": "LMTS/SMTS/MTS Data Engineer",
          "url": "https://careers.salesforce.com/en/jobs/jr321153/lmtssmtsmts-data-engineer/",
          "location": "Bangalore, Karnātaka, India",
          "department": "Software Engineering",
          "type": "Full time",
          "postedDate": "Tue, 17 Feb 2026 00:00:00 GMT"
        },
        {
          "id": "JR329416",
          "title": "Software Engineering SMTS",
          "url": "https://careers.salesforce.com/en/jobs/jr329416/software-engineering-smts/",
          "location": "Hyderabad, Telangāna, India",
          "department": "Software Engineering",
          "type": "Full time",
          "postedDate": "Thu, 12 Feb 2026 00:00:00 GMT"
        },
        {
          "id": "JR327535",
          "title": "Software Engineering SMTS- Tableau",
          "url": "https://careers.salesforce.com/en/jobs/jr327535/software-engineering-smts-tableau/",
          "location": "Bangalore, Karnātaka, India",
          "department": "Software Engineering",
          "type": "Full time",
          "postedDate": "Mon, 09 Feb 2026 00:00:00 GMT"
        },
        {
          "id": "JR310621",
          "title": "Software Engineering LMTS/SMTS - Big Data Infra (Spark/Kubernetes/Terraform/Helm))",
          "url": "https://careers.salesforce.com/en/jobs/jr310621/software-engineering-lmtssmts-big-data-infra-sparkkubernetesterraformhelm/",
          "location": "Hyderabad, Telangāna, India",
          "department": "Software Engineering",
          "type": "Full time",
          "postedDate": "Tue, 03 Feb 2026 00:00:00 GMT"
        },
        {
          "id": "JR312773",
          "title": "Performance Engineer (SMTS/LMTS)",
          "url": "https://careers.salesforce.com/en/jobs/jr312773/performance-engineer-smtslmts/",
          "location": "Hyderabad, Telangāna, India",
          "department": "Software Engineering",
          "type": "Full time",
          "postedDate": "Wed, 21 Jan 2026 00:00:00 GMT"
        },
        {
          "id": "JR288530",
          "title": "SMTS/LMTS Distributed Systems - Public Cloud, GCP",
          "url": "https://careers.salesforce.com/en/jobs/jr288530/smtslmts-distributed-systems-public-cloud-gcp/",
          "location": "Hyderabad, Telangāna, India",
          "department": "Software Engineering",
          "type": "Full time",
          "postedDate": "Wed, 14 Jan 2026 00:00:00 GMT"
        }
      ]
    },
    "booking": {
      "name": "Booking.com",
      "targetRole": "Senior Software Engineer",
      "careersUrl": "https://jobs.booking.com/booking/jobs?location=India",
      "jobs": [
        {
          "id": "27380",
          "title": "Senior Software Engineer II",
          "url": "https://careers-holdings-workingatbooking.icims.com/jobs/27380/login",
          "location": "Bangalore, India",
          "department": "Engineering",
          "type": "FULL_TIME",
          "postedDate": "2026-02-16T09:30:00+0000"
        }
      ]
    },
    "linkedin": {
      "name": "LinkedIn",
      "targetRole": "Senior Software Engineer",
      "careersUrl": "https://www.linkedin.com/jobs/search/?f_C=1337&geoId=102713980",
      "jobs": [
        {
          "id": "senior-software-engineer-fullstack-at-linkedin-4367410545",
          "title": "Sr. Software Engineer",
          "url": "https://in.linkedin.com/jobs/view/senior-software-engineer-fullstack-at-linkedin-4367410545",
          "location": "Bengaluru, Karnataka, India",
          "department": "LinkedIn",
          "type": "Full time",
          "postedDate": "2026-02-13"
        },
        {
          "id": "senior-software-engineer-systems-infrastructure-at-linkedin-4361321746",
          "title": "Senior Software Engineer - Fullstack",
          "url": "https://in.linkedin.com/jobs/view/senior-software-engineer-systems-infrastructure-at-linkedin-4361321746",
          "location": "Bengaluru, Karnataka, India",
          "department": "LinkedIn",
          "type": "Full time",
          "postedDate": "2026-01-30"
        },
        {
          "id": "sr-software-engineer-at-linkedin-4371267467",
          "title": "Senior Software Engineer, Systems Infrastructure",
          "url": "https://in.linkedin.com/jobs/view/sr-software-engineer-at-linkedin-4371267467",
          "location": "Bengaluru, Karnataka, India",
          "department": "LinkedIn",
          "type": "Full time",
          "postedDate": "2026-02-04"
        },
        {
          "id": "sr-staff-software-engineer-at-linkedin-4370936978",
          "title": "Sr. Software Engineer",
          "url": "https://in.linkedin.com/jobs/view/sr-staff-software-engineer-at-linkedin-4370936978",
          "location": "Bengaluru, Karnataka, India",
          "department": "LinkedIn",
          "type": "Full time",
          "postedDate": "2026-02-11"
        },
        {
          "id": "principal-staff-software-engineer-linkedin-marketing-solutions-at-linkedin-4361561423",
          "title": "Senior Software Engineer, Salesforce",
          "url": "https://in.linkedin.com/jobs/view/principal-staff-software-engineer-linkedin-marketing-solutions-at-linkedin-4361561423",
          "location": "Bengaluru, Karnataka, India",
          "department": "LinkedIn",
          "type": "Full time",
          "postedDate": "2026-02-12"
        }
      ]
    },
    "linkedin_easy": {
      "name": "LinkedIn Easy Apply",
      "targetRole": "Senior Software Engineer (all companies)",
      "careersUrl": "https://www.linkedin.com/jobs/search/?keywords=Senior+Software+Engineer&location=India&f_AL=true",
      "jobs": [
        {
          "id": "software-engineering-lmts-fullstack-at-salesforce-4371289750",
          "title": "MTS, Software Engineering",
          "url": "https://in.linkedin.com/jobs/view/software-engineering-lmts-fullstack-at-salesforce-4371289750",
          "location": "Hyderabad, Telangana, India",
          "department": "Salesforce",
          "type": "Easy Apply",
          "postedDate": "2026-02-18"
        },
        {
          "id": "agentforce-technical-manager-at-salesforce-4374718597",
          "title": "Agentforce Technical Manager",
          "url": "https://in.linkedin.com/jobs/view/agentforce-technical-manager-at-salesforce-4374718597",
          "location": "Bengaluru, Karnataka, India",
          "department": "Salesforce",
          "type": "Easy Apply",
          "postedDate": "2026-02-18"
        },
        {
          "id": "lmts-smts-mts-data-engineer-at-salesforce-4371636072",
          "title": "LMTS/SMTS/MTS Data Engineer",
          "url": "https://in.linkedin.com/jobs/view/lmts-smts-mts-data-engineer-at-salesforce-4371636072",
          "location": "Pune, Maharashtra, India",
          "department": "Salesforce",
          "type": "Easy Apply",
          "postedDate": "2026-02-17"
        },
        {
          "id": "mts-software-engineering-at-salesforce-4374776915",
          "title": "Performance Engineer LMTS",
          "url": "https://in.linkedin.com/jobs/view/mts-software-engineering-at-salesforce-4374776915",
          "location": "Hyderabad, Telangana, India",
          "department": "Salesforce",
          "type": "Easy Apply",
          "postedDate": "2026-02-17"
        },
        {
          "id": "software-engineering-lmts-fullstack-at-salesforce-4371405128",
          "title": "Principal Software Engineer / PMTS - Backend - Distributed Systems",
          "url": "https://in.linkedin.com/jobs/view/software-engineering-lmts-fullstack-at-salesforce-4371405128",
          "location": "Hyderabad, Telangana, India",
          "department": "Salesforce",
          "type": "Easy Apply",
          "postedDate": "2026-02-17"
        },
        {
          "id": "lead-member-technical-staff-distributed-scalable-systems-at-salesforce-4369915671",
          "title": "Salesforce Support Engineer - Industries &amp; Revenue Cloud",
          "url": "https://in.linkedin.com/jobs/view/lead-member-technical-staff-distributed-scalable-systems-at-salesforce-4369915671",
          "location": "Bengaluru, Karnataka, India",
          "department": "Salesforce",
          "type": "Easy Apply",
          "postedDate": "2026-02-17"
        },
        {
          "id": "senior-success-guide-salesforce-field-service-exp-mandatory-at-salesforce-4368076870",
          "title": "Salesforce Support Engineer - Industries &amp; Revenue Cloud",
          "url": "https://in.linkedin.com/jobs/view/senior-success-guide-salesforce-field-service-exp-mandatory-at-salesforce-4368076870",
          "location": "Hyderabad, Telangana, India",
          "department": "Salesforce",
          "type": "Easy Apply",
          "postedDate": "2026-02-17"
        },
        {
          "id": "principal-staff-software-engineer-linkedin-sales-solutions-at-linkedin-4361541506",
          "title": "Principal Staff Software Engineer - LinkedIn Talent Solutions",
          "url": "https://in.linkedin.com/jobs/view/principal-staff-software-engineer-linkedin-sales-solutions-at-linkedin-4361541506",
          "location": "Bengaluru, Karnataka, India",
          "department": "LinkedIn",
          "type": "Easy Apply",
          "postedDate": "2026-02-16"
        },
        {
          "id": "senior-software-engineer-fullstack-at-linkedin-4367410545",
          "title": "Sr. Software Engineer",
          "url": "https://in.linkedin.com/jobs/view/senior-software-engineer-fullstack-at-linkedin-4367410545",
          "location": "Bengaluru, Karnataka, India",
          "department": "LinkedIn",
          "type": "Easy Apply",
          "postedDate": "2026-02-13"
        },
        {
          "id": "lmts-smts-mts-data-engineer-at-salesforce-4371618964",
          "title": "Performance Engineer (SMTS/LMTS)",
          "url": "https://in.linkedin.com/jobs/view/lmts-smts-mts-data-engineer-at-salesforce-4371618964",
          "location": "Hyderabad, Telangana, India",
          "department": "Salesforce",
          "type": "Easy Apply",
          "postedDate": "2026-02-12"
        },
        {
          "id": "software-engineering-smts-tableau-at-salesforce-4367264362",
          "title": "Software Engineering SMTS",
          "url": "https://in.linkedin.com/jobs/view/software-engineering-smts-tableau-at-salesforce-4367264362",
          "location": "Hyderabad, Telangana, India",
          "department": "Salesforce",
          "type": "Easy Apply",
          "postedDate": "2026-02-12"
        },
        {
          "id": "software-engineering-architect-at-salesforce-4336841404",
          "title": "Software Engineering Architect",
          "url": "https://in.linkedin.com/jobs/view/software-engineering-architect-at-salesforce-4336841404",
          "location": "Hyderabad, Telangana, India",
          "department": "Salesforce",
          "type": "Easy Apply",
          "postedDate": "2026-02-12"
        },
        {
          "id": "performance-engineer-lmts-at-salesforce-4336951006",
          "title": "Software Engineering Architect",
          "url": "https://in.linkedin.com/jobs/view/performance-engineer-lmts-at-salesforce-4336951006",
          "location": "Bengaluru, Karnataka, India",
          "department": "Salesforce",
          "type": "Easy Apply",
          "postedDate": "2026-02-12"
        },
        {
          "id": "principal-staff-software-engineer-linkedin-marketing-solutions-at-linkedin-4361561423",
          "title": "Senior Software Engineer, Salesforce",
          "url": "https://in.linkedin.com/jobs/view/principal-staff-software-engineer-linkedin-marketing-solutions-at-linkedin-4361561423",
          "location": "Bengaluru, Karnataka, India",
          "department": "LinkedIn",
          "type": "Easy Apply",
          "postedDate": "2026-02-12"
        },
        {
          "id": "lmts-smts-mts-data-engineer-at-salesforce-4373915310",
          "title": "LMTS/SMTS/MTS Data Engineer",
          "url": "https://in.linkedin.com/jobs/view/lmts-smts-mts-data-engineer-at-salesforce-4373915310",
          "location": "Bengaluru, Karnataka, India",
          "department": "Salesforce",
          "type": "Easy Apply",
          "postedDate": "2026-02-11"
        },
        {
          "id": "smts-lmts-distributed-systems-public-cloud-gcp-at-salesforce-4328708628",
          "title": "LMTS/SMTS/MTS Data Engineer",
          "url": "https://in.linkedin.com/jobs/view/smts-lmts-distributed-systems-public-cloud-gcp-at-salesforce-4328708628",
          "location": "Hyderabad, Telangana, India",
          "department": "Salesforce",
          "type": "Easy Apply",
          "postedDate": "2026-02-11"
        },
        {
          "id": "lead-software-engineer-lmts-backend-distributed-systems-hyderabad-at-salesforce-4338749017",
          "title": "Software Engineering LMTS Fullstack",
          "url": "https://in.linkedin.com/jobs/view/lead-software-engineer-lmts-backend-distributed-systems-hyderabad-at-salesforce-4338749017",
          "location": "Hyderabad, Telangana, India",
          "department": "Salesforce",
          "type": "Easy Apply",
          "postedDate": "2026-02-11"
        },
        {
          "id": "software-engineering-lmts-pmts-architect-kafka-platform-engineer-at-salesforce-4361156809",
          "title": "LMTS - Lead Software Engineer - Network Security Platform",
          "url": "https://in.linkedin.com/jobs/view/software-engineering-lmts-pmts-architect-kafka-platform-engineer-at-salesforce-4361156809",
          "location": "Bengaluru, Karnataka, India",
          "department": "Salesforce",
          "type": "Easy Apply",
          "postedDate": "2026-02-11"
        },
        {
          "id": "sr-staff-software-engineer-at-linkedin-4370936978",
          "title": "Sr. Software Engineer",
          "url": "https://in.linkedin.com/jobs/view/sr-staff-software-engineer-at-linkedin-4370936978",
          "location": "Bengaluru, Karnataka, India",
          "department": "LinkedIn",
          "type": "Easy Apply",
          "postedDate": "2026-02-11"
        },
        {
          "id": "senior-staff-software-engineer-at-linkedin-4361561429",
          "title": "Sr. Staff Software Engineer",
          "url": "https://in.linkedin.com/jobs/view/senior-staff-software-engineer-at-linkedin-4361561429",
          "location": "Bengaluru, Karnataka, India",
          "department": "LinkedIn",
          "type": "Easy Apply",
          "postedDate": "2026-02-10"
        },
        {
          "id": "li-8",
          "title": "Software Engineering SMTS- Tableau",
          "url": "#",
          "location": "Bengaluru, Karnataka, India",
          "department": "Salesforce",
          "type": "Easy Apply",
          "postedDate": "2026-02-09"
        },
        {
          "id": "lmts-lead-software-engineer-network-security-platform-at-salesforce-4371458355",
          "title": "Lead Member Technical Staff_Distributed/Scalable Systems",
          "url": "https://in.linkedin.com/jobs/view/lmts-lead-software-engineer-network-security-platform-at-salesforce-4371458355",
          "location": "Hyderabad, Telangana, India",
          "department": "Salesforce",
          "type": "Easy Apply",
          "postedDate": "2026-02-06"
        },
        {
          "id": "software-engineering-lmts-smts-big-data-infra-spark-kubernetes-terraform-helm-at-salesforce-4341213951",
          "title": "SMTS/LMTS Distributed Systems - Public Cloud, GCP",
          "url": "https://in.linkedin.com/jobs/view/software-engineering-lmts-smts-big-data-infra-spark-kubernetes-terraform-helm-at-salesforce-4341213951",
          "location": "Hyderabad, Telangana, India",
          "department": "Salesforce",
          "type": "Easy Apply",
          "postedDate": "2026-02-05"
        },
        {
          "id": "software-engineering-smts-at-salesforce-4371855040",
          "title": "Software Engineering LMTS/SMTS - Big Data Infra (Spark/Kubernetes/Terraform/Helm))",
          "url": "https://in.linkedin.com/jobs/view/software-engineering-smts-at-salesforce-4371855040",
          "location": "Hyderabad, Telangana, India",
          "department": "Salesforce",
          "type": "Easy Apply",
          "postedDate": "2026-02-04"
        },
        {
          "id": "principal-software-engineer-pmts-backend-distributed-systems-at-salesforce-4336881385",
          "title": "Software Engineering LMTS/SMTS - Big Data Infra (Spark/Kubernetes/Terraform/Helm))",
          "url": "https://in.linkedin.com/jobs/view/principal-software-engineer-pmts-backend-distributed-systems-at-salesforce-4336881385",
          "location": "Hyderabad, Telangana, India",
          "department": "Salesforce",
          "type": "Easy Apply",
          "postedDate": "2026-02-04"
        },
        {
          "id": "sr-software-engineer-at-linkedin-4371267467",
          "title": "Senior Software Engineer, Systems Infrastructure",
          "url": "https://in.linkedin.com/jobs/view/sr-software-engineer-at-linkedin-4371267467",
          "location": "Bengaluru, Karnataka, India",
          "department": "LinkedIn",
          "type": "Easy Apply",
          "postedDate": "2026-02-04"
        },
        {
          "id": "principal-staff-software-engineer-linkedin-talent-solutions-at-linkedin-4373582051",
          "title": "Senior Staff Software Engineer",
          "url": "https://in.linkedin.com/jobs/view/principal-staff-software-engineer-linkedin-talent-solutions-at-linkedin-4373582051",
          "location": "Bengaluru, Karnataka, India",
          "department": "LinkedIn",
          "type": "Easy Apply",
          "postedDate": "2026-02-04"
        },
        {
          "id": "senior-software-engineer-salesforce-at-linkedin-4365241537",
          "title": "Principal Staff Software Engineer - Linkedin Sales Solutions",
          "url": "https://in.linkedin.com/jobs/view/senior-software-engineer-salesforce-at-linkedin-4365241537",
          "location": "Bengaluru, Karnataka, India",
          "department": "LinkedIn",
          "type": "Easy Apply",
          "postedDate": "2026-02-04"
        },
        {
          "id": "salesforce-support-engineer-industries-revenue-cloud-at-salesforce-4374103626",
          "title": "Software Engineering LMTS/PMTS/Architect (Kafka Platform Engineer)",
          "url": "https://in.linkedin.com/jobs/view/salesforce-support-engineer-industries-revenue-cloud-at-salesforce-4374103626",
          "location": "Bengaluru, Karnataka, India",
          "department": "Salesforce",
          "type": "Easy Apply",
          "postedDate": "2026-02-03"
        },
        {
          "id": "salesforce-support-engineer-industries-revenue-cloud-at-salesforce-4374117059",
          "title": "Software Engineering LMTS/PMTS/Architect (Kafka Platform Engineer)",
          "url": "https://in.linkedin.com/jobs/view/salesforce-support-engineer-industries-revenue-cloud-at-salesforce-4374117059",
          "location": "Hyderabad, Telangana, India",
          "department": "Salesforce",
          "type": "Easy Apply",
          "postedDate": "2026-02-03"
        },
        {
          "id": "software-engineering-smts-tableau-at-salesforce-4370558846",
          "title": "Software Engineering SMTS- Tableau",
          "url": "https://in.linkedin.com/jobs/view/software-engineering-smts-tableau-at-salesforce-4370558846",
          "location": "Hyderabad, Telangana, India",
          "department": "Salesforce",
          "type": "Easy Apply",
          "postedDate": "2026-01-30"
        },
        {
          "id": "li-9",
          "title": "Software Engineering MTS- Tableau",
          "url": "#",
          "location": "Bengaluru, Karnataka, India",
          "department": "Salesforce",
          "type": "Easy Apply",
          "postedDate": "2026-01-30"
        },
        {
          "id": "agentforce-technical-manager-at-salesforce-4374713744",
          "title": "Software Engineering SMTS- Tableau",
          "url": "https://in.linkedin.com/jobs/view/agentforce-technical-manager-at-salesforce-4374713744",
          "location": "Hyderabad, Telangana, India",
          "department": "Salesforce",
          "type": "Easy Apply",
          "postedDate": "2026-01-30"
        },
        {
          "id": "senior-software-engineer-systems-infrastructure-at-linkedin-4361321746",
          "title": "Senior Software Engineer - Fullstack",
          "url": "https://in.linkedin.com/jobs/view/senior-software-engineer-systems-infrastructure-at-linkedin-4361321746",
          "location": "Bengaluru, Karnataka, India",
          "department": "LinkedIn",
          "type": "Easy Apply",
          "postedDate": "2026-01-30"
        },
        {
          "id": "software-engineering-mts-tableau-at-salesforce-4367254642",
          "title": "Lead Software Engineer/LMTS - Backend - Distributed Systems - Hyderabad",
          "url": "https://in.linkedin.com/jobs/view/software-engineering-mts-tableau-at-salesforce-4367254642",
          "location": "Hyderabad, Telangana, India",
          "department": "Salesforce",
          "type": "Easy Apply",
          "postedDate": "2026-01-28"
        }
      ]
    }
  }
}